{
  "version": "7",
  "dialect": "postgresql",
  "entries": [
    {
      "idx": 0,
      "version": "7",
      "when": 1766661598769,
      "tag": "0000_upgrade_system_redesign",
      "breakpoints": true
    },
    {
      "idx": 1,
      "version": "7",
      "when": 1766661882475,
      "tag": "0001_remove_route_level",
      "breakpoints": true
    },
    {
      "idx": 2,
      "version": "7",
      "when": 1766699055508,
      "tag": "0002_active_job_single_xp",
      "breakpoints": true
    },
    {
      "idx": 3,
      "version": "7",
      "when": 1766925080586,
      "tag": "0003_eager_exiles",
      "breakpoints": true
    },
    {
      "idx": 4,
      "version": "7",
      "when": 1767130528621,
      "tag": "0004_refactor_employee_location",
      "breakpoints": true
    },
    {
      "idx": 5,
      "version": "7",
      "when": 1767423443671,
      "tag": "0005_add_regions_table",
      "breakpoints": true
    },
    {
      "idx": 6,
      "version": "7",
      "when": 1767442613928,
      "tag": "0006_drop_job_approx_fields",
      "breakpoints": true
    },
    {
      "idx": 7,
      "version": "7",
      "when": 1767446055475,
      "tag": "0007_low_grandmaster",
      "breakpoints": true
    },
    {
      "idx": 8,
      "version": "7",
      "when": 1767463378463,
      "tag": "0008_messy_victor_mancha",
      "breakpoints": true
    },
    {
      "idx": 9,
      "version": "7",
      "when": 1767511815268,
      "tag": "0009_square_lady_bullseye",
      "breakpoints": true
    },
    {
      "idx": 10,
      "version": "7",
      "when": 1767530361494,
      "tag": "0010_fuzzy_monster_badoon",
      "breakpoints": true
    },
    {
      "idx": 11,
      "version": "7",
      "when": 1767560049360,
      "tag": "0011_migrate_job_location_to_geometry_3857",
      "breakpoints": true
    },
    {
      "idx": 12,
      "version": "7",
      "when": 1767907434497,
      "tag": "0012_powerful_peter_quill",
      "breakpoints": true
    },
    {
      "idx": 13,
      "version": "7",
      "when": 1768685857819,
      "tag": "0013_vengeful_firestar",
      "breakpoints": true
    },
    {
      "idx": 14,
      "version": "7",
      "when": 1768858028830,
      "tag": "0014_thin_lionheart",
      "breakpoints": true
    },
    {
      "idx": 15,
      "version": "7",
      "when": 1768941579192,
      "tag": "0015_steady_warbird",
      "breakpoints": true
    },
    {
      "idx": 16,
      "version": "7",
      "when": 1768941760338,
      "tag": "0016_previous_silver_fox",
      "breakpoints": true
    },
    {
      "idx": 17,
      "version": "7",
      "when": 1769027707257,
      "tag": "0017_drop_addresses_use_places",
      "breakpoints": true
    },
    {
      "idx": 18,
      "version": "7",
      "when": 1769459681480,
      "tag": "0018_messy_charles_xavier",
      "breakpoints": true
    },
    {
      "idx": 19,
      "version": "7",
      "when": 1769460000000,
      "tag": "0019_active_places",
      "breakpoints": true
    },
    {
      "idx": 20,
      "version": "7",
      "when": 1769460100000,
      "tag": "0020_active_places_with_geom",
      "breakpoints": true
    },
    {
      "idx": 21,
      "version": "7",
      "when": 1769460200000,
      "tag": "0021_martin_tile_functions",
      "breakpoints": true
    },
    {
      "idx": 22,
      "version": "7",
      "when": 1769460300000,
      "tag": "0022_refine_tile_functions",
      "breakpoints": true
    },
    {
      "idx": 23,
      "version": "7",
      "when": 1769460400000,
      "tag": "0023_cap_tile_size",
      "breakpoints": true
    },
    {
      "idx": 24,
      "version": "7",
      "when": 1769460500000,
      "tag": "0024_cap_tile_size_lines_limit",
      "breakpoints": true
    },
    {
      "idx": 25,
      "version": "7",
      "when": 1770468984014,
      "tag": "0025_enhanced_active_places_with_geom",
      "breakpoints": true
    },
    {
      "idx": 26,
      "version": "7",
      "when": 1770498911632,
      "tag": "0026_add_active_places_place_id_index",
      "breakpoints": true
    }
  ]
}